setup.py
py_dsnt_probability/Binomialdistribution.py
py_dsnt_probability/Gaussiandistribution.py
py_dsnt_probability/Generaldistribution.py
py_dsnt_probability/__init__.py
py_dsnt_probability.egg-info/PKG-INFO
py_dsnt_probability.egg-info/SOURCES.txt
py_dsnt_probability.egg-info/dependency_links.txt
py_dsnt_probability.egg-info/not-zip-safe
py_dsnt_probability.egg-info/top_level.txt